{
    "btcpayprovider_api_key_required.txt": {
        "global_cache": false,
        "version_id": 1000070,
        "version_string": "1.0.0",
        "hash": "052769cb62ff0af584a8e6a61cfbb1ca"
    },
    "btcpayprovider_cannot_connect_to_store.txt": {
        "global_cache": false,
        "version_id": 1000070,
        "version_string": "1.0.0",
        "hash": "d150df02f010cdefacfabb5f9a42312b"
    },
    "btcpayprovider_host_required.txt": {
        "global_cache": false,
        "version_id": 1000070,
        "version_string": "1.0.0",
        "hash": "611456b181494136506016f5181eb1c9"
    },
    "btcpayprovider_invoice_creation_failed.txt": {
        "global_cache": false,
        "version_id": 1000070,
        "version_string": "1.0.0",
        "hash": "6d6dcdfbc71d35b3994706bf3dca45d6"
    },
    "btcpayprovider_secret_required.txt": {
        "global_cache": false,
        "version_id": 1000070,
        "version_string": "1.0.0",
        "hash": "a850c737e4784436cbb86f58ef0feb20"
    },
    "btcpayprovider_store_id_required.txt": {
        "global_cache": false,
        "version_id": 1000070,
        "version_string": "1.0.0",
        "hash": "1a273059c96929ea1713eedb738fb7e9"
    },
    "btcpayserver_api_key.txt": {
        "global_cache": false,
        "version_id": 1000070,
        "version_string": "1.0.0",
        "hash": "d876ff8da67c3731ae25d8335a4168b4"
    },
    "btcpayserver_host.txt": {
        "global_cache": false,
        "version_id": 1000070,
        "version_string": "1.0.0",
        "hash": "c2ca16d048ec66e04bca283eab048ec2"
    },
    "btcpayserver_secret.txt": {
        "global_cache": false,
        "version_id": 1000070,
        "version_string": "1.0.0",
        "hash": "1e6947ac7fb3a9529a9726eb692c8cc5"
    },
    "btcpayserver_store_id.txt": {
        "global_cache": false,
        "version_id": 1000070,
        "version_string": "1.0.0",
        "hash": "1feafb67c1da8183793afe1f61bce2f4"
    }
}